celery_signals/__init__.py
celery_signals/receivers.py
celery_signal_receivers-0.2.1.dist-info/LICENSE
celery_signal_receivers-0.2.1.dist-info/METADATA
celery_signal_receivers-0.2.1.dist-info/WHEEL
celery_signal_receivers-0.2.1.dist-info/RECORD
