Metadata-Version: 2.1
Name: celery-signal-receivers
Version: 0.2.1
Summary: Extension for the Django signal receivers to process them asynchronously as the Celery tasks.
Home-page: https://github.com/ivellios/celery-signal-receivers
License: MIT
Keywords: django,signals,celery
Author: Janusz Kamieński
Author-email: 200957+ivellios@users.noreply.github.com
Requires-Python: >=3.9,<4.0
Classifier: Framework :: Celery
Classifier: Framework :: Django :: 4.0
Classifier: Framework :: Django :: 4.1
Classifier: Framework :: Django :: 4.2
Classifier: Framework :: Django :: 5.0
Classifier: Framework :: Django :: 5.1
Classifier: License :: OSI Approved :: MIT License
Classifier: Operating System :: OS Independent
Classifier: Programming Language :: Python :: 3
Classifier: Programming Language :: Python :: 3.9
Classifier: Programming Language :: Python :: 3.10
Classifier: Programming Language :: Python :: 3.11
Classifier: Programming Language :: Python :: 3.12
Requires-Dist: Django (>=4.0,<6)
Requires-Dist: celery (>=5.3,<6.0)
Requires-Dist: django-unified-signals (>=0.2.1,<0.3.0)
Requires-Dist: setuptools (>=75.1.0,<76.0.0)
Project-URL: Repository, https://github.com/ivellios/celery-signal-receivers
